topsis/__init__.py
topsis/__main__.py
topsis_dev_102117155-0.0.1.dist-info/METADATA
topsis_dev_102117155-0.0.1.dist-info/WHEEL
topsis_dev_102117155-0.0.1.dist-info/entry_points.txt
topsis_dev_102117155-0.0.1.dist-info/top_level.txt
topsis_dev_102117155-0.0.1.dist-info/RECORD
